AbAffinity/__init__.py
AbAffinity/affinity_pred_model.py
AbAffinity/axial_attention.py
AbAffinity/constants.py
AbAffinity/create_dataset.py
AbAffinity/data.py
AbAffinity/esm2.py
AbAffinity/main.py
AbAffinity/modules.py
AbAffinity/multihead_attention.py
AbAffinity/rotary_embedding.py
AbAffinity/ESM2/__init__.py
AbAffinity/ESM2/axial_attention.py
AbAffinity/ESM2/constants.py
AbAffinity/ESM2/data.py
AbAffinity/ESM2/esm2.py
AbAffinity/ESM2/modules.py
AbAffinity/ESM2/multihead_attention.py
AbAffinity/ESM2/rotary_embedding.py
AbAffinity-0.1.2.dist-info/METADATA
AbAffinity-0.1.2.dist-info/WHEEL
AbAffinity-0.1.2.dist-info/top_level.txt
AbAffinity-0.1.2.dist-info/RECORD
