Metadata-Version: 2.1
Name: AbAffinity
Version: 0.1.2
Summary: Predict Affinity against SARS-CoV-2 HR2 peptide
Author: Faisal Bin Ashraf
Requires-Python: >=3.6
Requires-Dist: torch
Requires-Dist: numpy
Requires-Dist: matplotlib
Requires-Dist: textwrap3
